python/__init__.py
python/version.py
python/pytorch/__init__.py
python/tensorflow/__init__.py
python/tensorflow/input/__init__.py
silkynet-0.0.1.dist-info/METADATA
silkynet-0.0.1.dist-info/WHEEL
silkynet-0.0.1.dist-info/top_level.txt
silkynet-0.0.1.dist-info/RECORD
